{
  "model": "cross_sectional_rank",
  "frequency": "monthly",
  "universe": {
    "Health Care": "XLV",
    "Cons. Staples": "XLP",
    "Utilities": "XLU",
    "Energy": "XLE",
    "Materials": "XLB",
    "Industrials": "XLI",
    "Cons. Disc.": "XLY",
    "Financials": "XLF",
    "Real Estate": "VNQ",
    "Technology": "XLK",
    "Semiconductors": "SMH"
  },
  "common_start": "2004-09-30",
  "oos_start": "2010-01-31",
  "long_short_k": 3,
  "horizons": [
    "1m",
    "3m",
    "6m",
    "12m"
  ],
  "by_horizon": {
    "1": {
      "test": {
        "mom": {
          "ic": 0.07658851342186007,
          "ic_pos": 0.5714285714285714,
          "ls_ret": 0.0036030894011890497,
          "ls_hit": 0.5584415584415584,
          "ls_ir": 0.08495343348108103,
          "n": 77
        },
        "rsz": {
          "ic": 0.08677845797089528,
          "ic_pos": 0.5844155844155844,
          "ls_ret": 0.006654477739040437,
          "ls_hit": 0.5714285714285714,
          "ls_ir": 0.173528548224577,
          "n": 77
        },
        "enet": {
          "ic": 0.06507421687744748,
          "ic_pos": 0.5121951219512195,
          "ls_ret": 0.016183919664099492,
          "ls_hit": 0.6470588235294118,
          "ls_ir": 0.3609925521313346,
          "n": 41
        },
        "ensemble": {
          "ic": 0.10844830146513894,
          "ic_pos": 0.6097560975609756,
          "ls_ret": 0.00631707093125977,
          "ls_hit": 0.5609756097560976,
          "ls_ir": 0.13408960493036948,
          "n": 41
        }
      },
      "full": {
        "mom": {
          "ic": 0.04677987306310007,
          "ic_pos": 0.5329949238578681,
          "ls_ret": 0.0013676848320603628,
          "ls_hit": 0.5177664974619289,
          "ls_ir": 0.038253411424482645,
          "n": 197
        },
        "rsz": {
          "ic": 0.0077759782607242705,
          "ic_pos": 0.4720812182741117,
          "ls_ret": 0.0014857234827050409,
          "ls_hit": 0.467005076142132,
          "ls_ir": 0.046796509984337556,
          "n": 197
        },
        "enet": {
          "ic": 0.024934980298835015,
          "ic_pos": 0.4485981308411215,
          "ls_ret": 0.016183919664099492,
          "ls_hit": 0.6470588235294118,
          "ls_ir": 0.3609925521313346,
          "n": 107
        },
        "ensemble": {
          "ic": 0.046013039849679666,
          "ic_pos": 0.5234899328859061,
          "ls_ret": 0.0018017581203207981,
          "ls_hit": 0.5069444444444444,
          "ls_ir": 0.04984394422918571,
          "n": 149
        }
      },
      "avg_w": {
        "mom": 0.7959380020269141,
        "rsz": 0.11265243627049042,
        "enet": 0.09140956170259565
      }
    },
    "3": {
      "test": {
        "mom": {
          "ic": 0.0738516903626641,
          "ic_pos": 0.5333333333333333,
          "ls_ret": 0.0055289921826443605,
          "ls_hit": 0.5066666666666667,
          "ls_ir": 0.07168767422149934,
          "n": 75
        },
        "rsz": {
          "ic": 0.1344310317010259,
          "ic_pos": 0.6,
          "ls_ret": 0.021064993959902953,
          "ls_hit": 0.5733333333333334,
          "ls_ir": 0.3170376134823607,
          "n": 75
        },
        "enet": {
          "ic": 5.071530400849766e-18,
          "ic_pos": 0.41025641025641024,
          "ls_ret": NaN,
          "ls_hit": NaN,
          "ls_ir": NaN,
          "n": 39
        },
        "ensemble": {
          "ic": 0.059264966542871826,
          "ic_pos": 0.5384615384615384,
          "ls_ret": 0.005439374545464095,
          "ls_hit": 0.48717948717948717,
          "ls_ir": 0.06396336909851828,
          "n": 39
        }
      },
      "full": {
        "mom": {
          "ic": 0.04715749567703681,
          "ic_pos": 0.517948717948718,
          "ls_ret": 0.001267436826289787,
          "ls_hit": 0.48205128205128206,
          "ls_ir": 0.02014154549018904,
          "n": 195
        },
        "rsz": {
          "ic": -0.004505154757533812,
          "ic_pos": 0.49230769230769234,
          "ls_ret": 0.0018784971457628992,
          "ls_hit": 0.49230769230769234,
          "ls_ir": 0.032185918797763176,
          "n": 195
        },
        "enet": {
          "ic": 2.9234041012660422e-18,
          "ic_pos": 0.43410852713178294,
          "ls_ret": NaN,
          "ls_hit": NaN,
          "ls_ir": NaN,
          "n": 129
        },
        "ensemble": {
          "ic": 0.025244373955274565,
          "ic_pos": 0.5068493150684932,
          "ls_ret": -0.00070675411258053,
          "ls_hit": 0.4696969696969697,
          "ls_ir": -0.010790287470850563,
          "n": 146
        }
      },
      "avg_w": {
        "mom": 0.802692047966127,
        "rsz": 0.1114493661752869,
        "enet": 0.08585858585858602
      }
    },
    "6": {
      "test": {
        "mom": {
          "ic": 0.1384082858212266,
          "ic_pos": 0.5972222222222222,
          "ls_ret": 0.00739176655404747,
          "ls_hit": 0.5694444444444444,
          "ls_ir": 0.06424044780528526,
          "n": 72
        },
        "rsz": {
          "ic": 0.22143644980343183,
          "ic_pos": 0.6388888888888888,
          "ls_ret": 0.04221356349587232,
          "ls_hit": 0.6944444444444444,
          "ls_ir": 0.44465070543375085,
          "n": 72
        },
        "enet": {
          "ic": 2.675698926347831e-18,
          "ic_pos": 0.42857142857142855,
          "ls_ret": NaN,
          "ls_hit": NaN,
          "ls_ir": NaN,
          "n": 42
        },
        "ensemble": {
          "ic": 0.1736672070389777,
          "ic_pos": 0.6507936507936508,
          "ls_ret": 0.019577373748084003,
          "ls_hit": 0.6507936507936508,
          "ls_ir": 0.21387175513391343,
          "n": 63
        }
      },
      "full": {
        "mom": {
          "ic": 0.08040837819224449,
          "ic_pos": 0.546875,
          "ls_ret": 0.005015791918402024,
          "ls_hit": 0.5260416666666666,
          "ls_ir": 0.055462684273586166,
          "n": 192
        },
        "rsz": {
          "ic": 0.012562765812148277,
          "ic_pos": 0.4739583333333333,
          "ls_ret": 0.0054378864677785445,
          "ls_hit": 0.4947916666666667,
          "ls_ir": 0.06253840017984796,
          "n": 192
        },
        "enet": {
          "ic": -0.037569515864696916,
          "ic_pos": 0.3968253968253968,
          "ls_ret": -0.0711540741319125,
          "ls_hit": 0.16666666666666666,
          "ls_ir": -1.1638558604694433,
          "n": 126
        },
        "ensemble": {
          "ic": 0.07406406597549937,
          "ic_pos": 0.5519125683060109,
          "ls_ret": 0.006473033385783623,
          "ls_hit": 0.5409836065573771,
          "ls_ir": 0.08152662548209054,
          "n": 183
        }
      },
      "avg_w": {
        "mom": 0.8924206011998733,
        "rsz": 0.09727370270164086,
        "enet": 0.010305696098485797
      }
    },
    "12": {
      "test": {
        "mom": {
          "ic": 0.05068049486921884,
          "ic_pos": 0.48484848484848486,
          "ls_ret": -0.032744587145210544,
          "ls_hit": 0.45454545454545453,
          "ls_ir": -0.18453193410537638,
          "n": 66
        },
        "rsz": {
          "ic": 0.27652622007383204,
          "ic_pos": 0.7424242424242424,
          "ls_ret": 0.09693966088161238,
          "ls_hit": 0.7575757575757576,
          "ls_ir": 0.8436058799607464,
          "n": 66
        },
        "enet": {
          "ic": 0.19918866250181042,
          "ic_pos": 0.5333333333333333,
          "ls_ret": 0.18962526775912006,
          "ls_hit": 1.0,
          "ls_ir": 1.5886519391641918,
          "n": 30
        },
        "ensemble": {
          "ic": 0.062037113046967275,
          "ic_pos": 0.5208333333333334,
          "ls_ret": -0.022911040108706107,
          "ls_hit": 0.4375,
          "ls_ir": -0.14448034395742748,
          "n": 48
        }
      },
      "full": {
        "mom": {
          "ic": 0.060848450508208675,
          "ic_pos": 0.521505376344086,
          "ls_ret": -9.671374719940696e-05,
          "ls_hit": 0.4946236559139785,
          "ls_ir": -0.0007060708932576092,
          "n": 186
        },
        "rsz": {
          "ic": 0.01146373777660225,
          "ic_pos": 0.5053763440860215,
          "ls_ret": 0.01669015929596216,
          "ls_hit": 0.5161290322580645,
          "ls_ir": 0.1406224817281458,
          "n": 186
        },
        "enet": {
          "ic": 0.04010389846887971,
          "ic_pos": 0.4215686274509804,
          "ls_ret": 0.07658720977116394,
          "ls_hit": 0.5833333333333334,
          "ls_ir": 0.5290178827787096,
          "n": 102
        },
        "ensemble": {
          "ic": 0.043474107543713184,
          "ic_pos": 0.503448275862069,
          "ls_ret": 0.003715563593817725,
          "ls_hit": 0.46511627906976744,
          "ls_ir": 0.027876515694535014,
          "n": 145
        }
      },
      "avg_w": {
        "mom": 0.6281164617331991,
        "rsz": 0.11040312861041357,
        "enet": 0.26148040965638736
      }
    }
  }
}